scallfold/cli.py
scallfold/compatibility.py
scallfold/project/generator.py
scallfold/project/structure.py
scallfold/templates/clean/.gitignore
scallfold/templates/clean/README.md.j2
scallfold/templates/clean/main.py.j2
scallfold/templates/clean/package_init.py.j2
scallfold/templates/clean/pyproject.toml.j2
scallfold/templates/clean/test_basic.py.j2
scallfold/templates/structured/.env
scallfold/templates/structured/.gitignore
scallfold/templates/structured/README.md.j2
scallfold/templates/structured/main.py.j2
scallfold/templates/structured/pyproject.toml.j2
scallfold/templates/structured/requirements.txt.j2
scallfold/templates/structured/test_basic.py.j2
scallfold/templates/structured/api/dependencies.py.j2
scallfold/templates/structured/api/routes.py.j2
scallfold/templates/structured/core/config.py.j2
scallfold/templates/structured/core/database.py.j2
scallfold/templates/structured/models/base.py.j2
scallfold/templates/structured/models/user.py.j2
scallfold/utils/filesystem.py
scallfold/utils/prompts.py
scallfold/utils/templating.py
scallpy-0.1.3.dist-info/METADATA
scallpy-0.1.3.dist-info/WHEEL
scallpy-0.1.3.dist-info/entry_points.txt
scallpy-0.1.3.dist-info/licenses/LICENSE
scallpy-0.1.3.dist-info/RECORD
