Metadata-Version: 2.4
Name: scallpy
Version: 0.1.3
Summary: A command-line tool to scaffold FastAPI projects, inspired by vitejs.
Project-URL: Homepage, https://github.com/jara505/fastapi-scallfolding
Project-URL: Bug Tracker, https://github.com/jara505/fastapi-scallfolding/issues
Author-email: Juan Ignacio Jara Caceres <juanignaciojara505@gmail.com>
License-File: LICENSE
Classifier: License :: OSI Approved :: MIT License
Classifier: Operating System :: OS Independent
Classifier: Programming Language :: Python :: 3
Classifier: Programming Language :: Python :: 3.10
Classifier: Programming Language :: Python :: 3.11
Classifier: Programming Language :: Python :: 3.12
Requires-Python: >=3.10
Requires-Dist: inquirerpy>=0.3.4
Requires-Dist: jinja2>=3.1.2
Requires-Dist: typer[all]>=0.9.0
Provides-Extra: dev
Requires-Dist: pytest>=7.0.0; extra == 'dev'
